gusto_embedded/__init__.py
gusto_embedded/_hooks/__init__.py
gusto_embedded/_hooks/registration.py
gusto_embedded/_hooks/sdkhooks.py
gusto_embedded/_hooks/types.py
gusto_embedded/_version.py
gusto_embedded/achtransactions.py
gusto_embedded/bankaccounts.py
gusto_embedded/basesdk.py
gusto_embedded/companies.py
gusto_embedded/companyattachment_sdk.py
gusto_embedded/companyattachments.py
gusto_embedded/companybenefits.py
gusto_embedded/companyforms.py
gusto_embedded/contractordocuments.py
gusto_embedded/contractorforms.py
gusto_embedded/contractorpaymentgroups.py
gusto_embedded/contractorpaymentmethod_sdk.py
gusto_embedded/contractorpaymentmethods.py
gusto_embedded/contractorpayments.py
gusto_embedded/contractors.py
gusto_embedded/departments.py
gusto_embedded/earningtypes.py
gusto_embedded/employeeaddresses.py
gusto_embedded/employeebenefits.py
gusto_embedded/employeeemployments.py
gusto_embedded/employeeforms.py
gusto_embedded/employeepaymentmethod_sdk.py
gusto_embedded/employeepaymentmethods.py
gusto_embedded/employees.py
gusto_embedded/employeetaxsetup.py
gusto_embedded/events.py
gusto_embedded/externalpayrolls.py
gusto_embedded/federaltaxdetails_sdk.py
gusto_embedded/flows.py
gusto_embedded/garnishments.py
gusto_embedded/generateddocuments.py
gusto_embedded/historicalemployees.py
gusto_embedded/holidaypaypolicies.py
gusto_embedded/httpclient.py
gusto_embedded/i9verification.py
gusto_embedded/industryselection.py
gusto_embedded/introspection.py
gusto_embedded/invoices.py
gusto_embedded/jobsandcompensations.py
gusto_embedded/locations.py
gusto_embedded/models/__init__.py
gusto_embedded/models/accruing_time_off_hour.py
gusto_embedded/models/accruing_time_off_hour_object.py
gusto_embedded/models/ach_transaction.py
gusto_embedded/models/admin.py
gusto_embedded/models/apierror.py
gusto_embedded/models/authentication.py
gusto_embedded/models/benefit_summary.py
gusto_embedded/models/benefit_type_requirements.py
gusto_embedded/models/child_support_data.py
gusto_embedded-0.2.4.dist-info/METADATA
gusto_embedded-0.2.4.dist-info/WHEEL
gusto_embedded-0.2.4.dist-info/RECORD
